sa_modelcrud/__init__.py
sa_modelcrud/crud/__init__.py
sa_modelcrud/crud/base.py
sa_modelcrud/exceptions/__init__.py
sa_modelcrud/exceptions/crud.py
sa_modelcrud/models/__init__.py
sa_modelcrud/models/base.py
sa_modelcrud/models/mixins.py
sa_modelcrud/tests/__init__.py
sa_modelcrud/tests/config.py
sa_modelcrud/tests/crud.py
sa_modelcrud/tests/models.py
sa_modelcrud/tests/schemas.py
sa_modelcrud/tests/session.py
sa_modelcrud/tests/test_crud.py
sa_modelcrud/tests/test_crud_base.py
sa_modelcrud-0.4.1.dist-info/LICENSE
sa_modelcrud-0.4.1.dist-info/METADATA
sa_modelcrud-0.4.1.dist-info/WHEEL
sa_modelcrud-0.4.1.dist-info/RECORD
