Metadata-Version: 2.1
Name: sa-modelcrud
Version: 0.4.1
Summary: Model CRUD manager to handle databases with asynchronous SQLAlchemy sessions
License: MIT
Author: Lucas Lucyk
Author-email: llucyk@grupospec.com
Requires-Python: >=3.8,<4.0
Classifier: License :: OSI Approved :: MIT License
Classifier: Programming Language :: Python :: 3
Classifier: Programming Language :: Python :: 3.8
Classifier: Programming Language :: Python :: 3.9
Classifier: Programming Language :: Python :: 3.10
Classifier: Programming Language :: Python :: 3.11
Requires-Dist: pydantic (>=2.4.2,<3.0.0)
Requires-Dist: sqlalchemy (>=2.0.22,<3.0.0)
